{
  "token_id": "0d3070dc66435ca3f1dab0f816438aadd758dabeaa35e6de855c75c1424f4e4b",
  "ticker": "BONK",
  "market_cap": 1105.5528855827886,
  "price": 0.0000011055528855827887,
  "liquidity": 7.582063,
  "circulating_supply": 0,
  "outliers_filtered": true,
  "pool_count": 1,
  "original_pool_count": 2,
  "median_used": true,
  "suspicious_liquidity": true,
  "price_from_average_price": false,
  "mcap_liquidity_ratio": "145.81",
  "token_age": 739354,
  "trust_assessment": {
    "score": 0,
    "level": "Very Low",
    "penalties": [
      {
        "reason": "Single liquidity pool",
        "points": -30
      },
      {
        "reason": "Extremely high market cap to liquidity ratio (145.81:1)",
        "points": -40
      },
      {
        "reason": "Extremely low liquidity",
        "points": -70
      },
      {
        "reason": "Suspicious liquidity distribution with low total liquidity",
        "points": -30
      }
    ],
    "bonuses": [
      {
        "reason": "Token has existed for more than a year",
        "points": 15
      }
    ]
  },
  "honeypot_risk": true,
  "validation": {
    "valid": false,
    "reasons": [
      "Insufficient liquidity (7.58 ADA) - minimum threshold is 500 ADA",
      "Potential honeypot token: Low trust score"
    ],
    "trustScore": 0
  },
  "updated_at": "2025-04-14T15:55:51.500Z"
}