{
  "token_id": "8e969e8e238886405a1d6a43a6c0cfa8e94f15eb0e3db805c00c4f58546f6e7920746865207469676572",
  "ticker": "TONY",
  "token_ascii": "Tony Tiger",
  "market_cap": 3716.0015263918353,
  "price": 0.0000037160015263918352,
  "liquidity": 3293.051305,
  "circulating_supply": 0,
  "outliers_filtered": true,
  "pool_count": 1,
  "original_pool_count": 2,
  "median_used": true,
  "suspicious_liquidity": true,
  "price_from_average_price": false,
  "mcap_liquidity_ratio": "1.13",
  "token_age": 146,
  "trust_assessment": {
    "score": 45,
    "level": "Moderate",
    "penalties": [
      {
        "reason": "Single liquidity pool",
        "points": -30
      },
      {
        "reason": "Suspicious liquidity distribution with low total liquidity",
        "points": -30
      }
    ],
    "bonuses": [
      {
        "reason": "Token has existed for more than a month",
        "points": 5
      }
    ]
  },
  "honeypot_risk": false,
  "validation": {
    "valid": true,
    "reasons": [],
    "trustScore": 0
  },
  "updated_at": "2025-04-14T15:58:02.975Z"
}